rwp/SSPade.py
rwp/SSPade3d.py
rwp/WPVis.py
rwp/__init__.py
rwp/_cn_utils.cp35-win_amd64.pyd
rwp/_utils.py
rwp/antennas.py
rwp/contfrac.cp35-win_amd64.pyd
rwp/crank_nicolson.py
rwp/environment.py
rwp/field.py
rwp/petool.py
rwp/ssf.py
rwp/task.py
rwp/tests.py
rwp/tropospheric_attenuation.py
rwp/urban.py
rwp-1.1.dist-info/METADATA
rwp-1.1.dist-info/RECORD
rwp-1.1.dist-info/WHEEL
rwp-1.1.dist-info/top_level.txt
